files/verilog/full_adder.v
module fa (
    input a, b, cin, output sum, cout
);
    assign {cout, sum} = a + b + cin;
endmodule

files/verilog/tb.v
`timescale 1ps/1ps
module tb;
    reg a, b, cin;
    wire sum, cout;
    fa fa1(a, b, cin, sum, cout);
    initial begin
        $dumpfile("fa.vcd");
        $dumpvars(1);
    end
    initial begin
        a = 0; b = 0; cin = 0;
        #5 a = 0; b = 0; cin = 1;
        #5 a = 0; b = 1; cin = 0;
        #5 a = 0; b = 1; cin = 1;
        #5 a = 1; b = 0; cin = 0;
        #5 a = 1; b = 0; cin = 1;
        #5 a = 1; b = 1; cin = 0;
        #5 a = 1; b = 1; cin = 1;
        #5 a = 0; b = 0; cin = 0;
    end
    initial begin
        $monitor("simtime = %0g, a = %b, b = %b, cin = %b, sum = %b, cout = %b",
         $time, a, b, cin, sum, cout);
    end
endmodule

files/verilog/fa.vcd
$date
	Fri Mar 14 20:40:34 2025
$end
$version
	Icarus Verilog
$end
$timescale
	1ps
$end
$scope module tb $end
$var wire 1 ! sum $end
$var wire 1 " cout $end
$var reg 1 # a $end
$var reg 1 $ b $end
$var reg 1 % cin $end
$upscope $end
$enddefinitions $end
$comment Show the parameter values. $end
$dumpall
$end
#0
$dumpvars
0%
0$
0#
0"
0!
$end
#5
1!
1%
#10
0%
1$
#15
0!
1"
1%
#20
0"
1!
0%
0$
1#
#25
0!
1"
1%
#30
0%
1$
#35
1!
1%
#40
0"
0!
0%
0$
0#
